readwise_sdk/__init__.py
readwise_sdk/_utils.py
readwise_sdk/client.py
readwise_sdk/exceptions.py
readwise_sdk/cli/__init__.py
readwise_sdk/cli/main.py
readwise_sdk/contrib/__init__.py
readwise_sdk/contrib/batch_sync.py
readwise_sdk/contrib/document_import.py
readwise_sdk/contrib/highlight_push.py
readwise_sdk/managers/__init__.py
readwise_sdk/managers/async_managers.py
readwise_sdk/managers/books.py
readwise_sdk/managers/documents.py
readwise_sdk/managers/highlights.py
readwise_sdk/managers/sync.py
readwise_sdk/v2/__init__.py
readwise_sdk/v2/async_client.py
readwise_sdk/v2/client.py
readwise_sdk/v2/models.py
readwise_sdk/v3/__init__.py
readwise_sdk/v3/async_client.py
readwise_sdk/v3/client.py
readwise_sdk/v3/models.py
readwise_sdk/workflows/__init__.py
readwise_sdk/workflows/digest.py
readwise_sdk/workflows/inbox.py
readwise_sdk/workflows/poller.py
readwise_sdk/workflows/tags.py
readwise_plus-0.1.3.dist-info/METADATA
readwise_plus-0.1.3.dist-info/WHEEL
readwise_plus-0.1.3.dist-info/entry_points.txt
readwise_plus-0.1.3.dist-info/RECORD
