Metadata-Version: 2.4
Name: readwise-plus
Version: 0.1.3
Summary: Comprehensive Python SDK for Readwise with high-level workflow abstractions. Supports V2 (highlights/books) and V3 (Reader) APIs with managers, workflows, and CLI.
Project-URL: Homepage, https://github.com/EvanOman/readwise-plus
Project-URL: Repository, https://github.com/EvanOman/readwise-plus
Project-URL: Issues, https://github.com/EvanOman/readwise-plus/issues
Author: Evan Oman
License-Expression: MIT
Keywords: api,digest,highlights,reader,readwise,sdk,workflows
Classifier: Development Status :: 3 - Alpha
Classifier: Intended Audience :: Developers
Classifier: License :: OSI Approved :: MIT License
Classifier: Programming Language :: Python :: 3
Classifier: Programming Language :: Python :: 3.12
Classifier: Programming Language :: Python :: 3.13
Classifier: Topic :: Software Development :: Libraries :: Python Modules
Classifier: Typing :: Typed
Requires-Python: >=3.12
Requires-Dist: httpx>=0.27.0
Requires-Dist: pydantic>=2.0.0
Provides-Extra: cli
Requires-Dist: rich>=14.0.0; extra == 'cli'
Requires-Dist: typer>=0.21.0; extra == 'cli'
